README.rst
setup.py
oracle_connection/__init__.py
oracle_connection/connect_models.py
oracle_connection/operate.py
oracle_connection.egg-info/PKG-INFO
oracle_connection.egg-info/SOURCES.txt
oracle_connection.egg-info/dependency_links.txt
oracle_connection.egg-info/requires.txt
oracle_connection.egg-info/top_level.txt