Metadata-Version: 1.1
Name: oracle-connection
Version: 0.1.2
Summary: A new way to operate oracle
Home-page: https://github.com/Thchoonlophon/oracle-connection
Author: Jingxuan
Author-email: qian_chen_jin@163.com
License: MIT License
Platform: UNKNOWN
Classifier: License :: OSI Approved :: MIT License
Classifier: Programming Language :: Python :: 3
Classifier: Programming Language :: Python :: 3.6
Classifier: Programming Language :: Python :: 3.7
Classifier: Programming Language :: Python :: 3.8
